fengling/__init__.py
fengling/progress.py
fengling-0.1.0.dist-info/licenses/LICENSE
fengling-0.1.0.dist-info/METADATA
fengling-0.1.0.dist-info/WHEEL
fengling-0.1.0.dist-info/top_level.txt
fengling-0.1.0.dist-info/RECORD
