Metadata-Version: 2.4
Name: fengling
Version: 0.1.0
Summary: 一个基于emoji的风铃进度条库,肥城泰西的风铃
Home-page: https://github.com/ala/fengling
Author: ala
Author-email: ala9981@163.com
Keywords: progress bar,emoji,animation,terminal,cli
Classifier: Programming Language :: Python :: 3
Classifier: License :: OSI Approved :: MIT License
Classifier: Operating System :: OS Independent
Classifier: Development Status :: 4 - Beta
Classifier: Intended Audience :: Developers
Classifier: Topic :: Software Development :: Libraries :: Python Modules
Requires-Python: >=3.6
License-File: LICENSE
Dynamic: author
Dynamic: author-email
Dynamic: classifier
Dynamic: description
Dynamic: description-content-type
Dynamic: home-page
Dynamic: keywords
Dynamic: license-file
Dynamic: requires-python
Dynamic: summary
